<?xml version="1.0" encoding="utf-8"?>
<I c="Trait" i="trait" m="traits.traits" n="trait_University_ComputerScienceDegreeBS" s="218129">
  <L n="ages">
    <E>TEEN</E>
    <E>ADULT</E>
    <E>BABY</E>
    <E>CHILD</E>
    <E>TODDLER</E>
    <E>ELDER</E>
    <E>YOUNGADULT</E>
    <E>INFANT</E>
  </L>
  <T n="buffs_add_on_spawn_only">False</T>
  <T n="display_name">0xF87853E<!--Computer Science Degree--></T>
  <T n="display_name_gender_neutral">0x52113426<!--Computer Science Degree--></T>
  <T n="icon" p="InEP08\UI\Icons\DegreeSystem\DegreeSystem_computerScience_gold_main.png">2f7d0004:00000000:6cfc203e2fe95cdf</T>
  <L n="provided_mixers">
    <U>
      <T n="key">13998<!--sim_Chat--></T>
      <L n="value">
        <T>226662<!--mixer_Social_UniversityRivalry_TauntAboutUniversitySuperiority--></T>
      </L>
    </U>
  </L>
  <L n="species">
    <E />
  </L>
  <L n="super_affordances">
    <T>226053<!--sI_UniversityRivalry_SchoolCheer_Science--></T>
  </L>
  <L n="target_super_affordances">
    <U>
      <T n="affordance">228418<!--sI_UniversityRivalry_Autonomous_Taunt--></T>
    </U>
  </L>
  <T n="trait_description">0xBE523D95<!--This Sim has earned a Distinguished Degree in Computer Science--></T>
  <T n="trait_origin_description">0x655A1830<!--(From Foxbury Institute)--></T>
  <E n="trait_type">UNIVERSITY_DEGREE</E>
</I>