<?xml version="1.0" encoding="utf-8"?>
<I c="Trait" i="trait" m="traits.traits" n="trait_CarryableInfant_PreferredCarrier_Pink" s="307875">
  <L n="ages">
    <E>INFANT</E>
  </L>
  <T n="display_name">0x9D409444<!--Infant Wrangler - White with Pink Accents--></T>
  <T n="display_name_gender_neutral">0xCD8E2A54<!--Infant Wrangler - White with Pink Accents--></T>
  <T n="icon" p="InEP13\UI\Icons\Inventory\BabyCarrier\Inventory_BabyCarrierPink.png">2f7d0004:00000000:e41d2d53aabc3116</T>
  <V n="loot_on_trait_add" t="enabled">
    <L n="enabled">
      <T>331906<!--loot_Infant_Carry_Back_RemoveOtherTraits_Pink--></T>
    </L>
  </V>
  <L n="species">
    <E />
  </L>
  <E n="trait_type">INFANT_CARRIER</E>
</I>