<?xml version="1.0" encoding="utf-8"?>
<I c="Objective" i="objective" m="event_testing.objective_tuning" n="objective_Asp_Deviance_B4_2" s="25315">
  <L n="completion_loot">
    <T>273578<!--loot_Want_AspirationCompleted--></T>
  </L>
  <T n="display_text">0xB3AF80F8<!--Perform Voodoo {1.Number} Times--></T>
  <V n="objective_completion_type" t="iterations">
    <U n="iterations">
      <T n="iterations_required_to_pass">5</T>
    </U>
  </V>
  <V n="objective_test" t="ran_interaction_test">
    <U n="ran_interaction_test">
      <L n="affordances">
        <T>14531<!--voodooDoll_Do_Cuddle--></T>
        <T>14532<!--voodooDoll_Do_Frolic--></T>
        <T>14534<!--voodooDoll_Do_Poke--></T>
        <T>14535<!--voodooDoll_Do_Soak--></T>
        <T>14536<!--voodooDoll_Do_Tickle--></T>
        <T>24421<!--voodooDoll_Cuddle--></T>
        <T>24422<!--voodooDoll_Frolic--></T>
        <T>24420<!--voodooDoll_Poke--></T>
        <T>24423<!--voodooDoll_Soak--></T>
        <T>24425<!--voodooDoll_Tickle--></T>
        <T>14540<!--voodooDoll_Summon--></T>
      </L>
    </U>
  </V>
  <T n="satisfaction_points">750</T>
  <T n="tooltip">0xFCA12D34<!--Click on the Voodoo Doll to perform Voodoo on another Sim. Don't forget to bind the Voodoo Doll to a Sim first.--></T>
</I>