<?xml version="1.0" encoding="utf-8"?>
<I c="CommodityBasedObjectState" i="object_state" m="objects.components.state" n="StyleBoard_Progress_CommodityState" s="198119">
  <L n="_values">
    <T>198118<!--styleBoard_Progress_Step1--></T>
    <T>198142<!--styleBoard_Progress_Step2--></T>
    <T>198117<!--styleBoard_Progress_Step3--></T>
    <T>198116<!--styleBoard_Progress_Step4--></T>
    <T>198230<!--styleBoard_Progress_Finish--></T>
    <T>203197<!--styleBoard_Progress_Step9--></T>
    <T>203198<!--styleBoard_Progress_Step5--></T>
    <T>203199<!--styleBoard_Progress_Step6--></T>
    <T>203200<!--styleBoard_Progress_Step7--></T>
    <T>203201<!--styleBoard_Progress_Step8--></T>
  </L>
  <T n="linked_stat">198120<!--statistic_Styleboard_Completion--></T>
</I>