<?xml version="1.0" encoding="utf-8"?>
<I c="CommodityBasedObjectStateValue" i="object_state" m="objects.components.state" n="recreationTable_puzzleProgress_values_25_percent_size3" s="317292">
  <U n="new_client_state">
    <V n="geometry_state" t="apply_new_value">
      <V n="apply_new_value" t="set_to_custom_value">
        <T n="set_to_custom_value">progress</T>
      </V>
    </V>
    <V n="material_state" t="apply_new_value">
      <U n="apply_new_value">
        <V n="state_name" t="set_to_custom_value">
          <T n="set_to_custom_value">size03</T>
        </V>
      </U>
    </V>
    <V n="painting_reveal_level" t="apply_new_value">
      <T n="apply_new_value">1</T>
    </V>
    <V n="painting_state" t="apply_new_value">
      <U n="apply_new_value">
        <V n="overlay_texture_id" t="set_texture">
          <U n="set_texture">
            <T n="texture_key" p="InGame\Objects\Buy\GamePuzzle\gamePuzzle_overlay_size03.tga">2f7d0006:00000000:ea9ac78904508c65</T>
          </U>
        </V>
        <V n="reveal_texture_id" t="set_texture">
          <U n="set_texture">
            <T n="texture_key" p="InGame\Objects\Buy\GamePuzzle\gamePuzzle_reveal_size03A.tga">2f7d0006:00000000:ae4274359287bf55</T>
          </U>
        </V>
        <V n="use_for_puzzle" t="reveal_texture_id_B">
          <V n="reveal_texture_id_B" t="set_texture">
            <U n="set_texture">
              <T n="texture_key" p="InGame\Objects\Buy\GamePuzzle\gamePuzzle_reveal_size03B.tga">2f7d0006:00000000:ae4274359287bf56</T>
            </U>
          </V>
        </V>
      </U>
    </V>
  </U>
  <U n="range">
    <T n="lower_bound">10</T>
    <T n="upper_bound">25</T>
  </U>
</I>