<?xml version="1.0" encoding="utf-8"?>
<I c="Tutorial" i="tutorial" m="tutorials.tutorial" n="EP13_tutorial_InfantCareObjects" s="330564">
  <T n="category">330152<!--tutorial_Category_GrowingTogether--></T>
  <T n="name">0x765AF79F<!--Infant Care Objects--></T>
  <L n="slides">
    <U>
      <T n="image" p="InEP13\UI\Lessons\EP13_InfantCareObjects_1.png">2f7d0004:00000000:ef8d00c718ce4a8a</T>
      <T n="text">0x3866D0FC<!--Caregivers can now change diapers for Infant and Toddler Sims by using the Changing Table! Different Changing Tables can be purchased directly from Build Buy mode with or without a Diaper Pail attached. If an Infant Sim is left with a dirty diaper for too long they can get a diaper rash. --></T>
    </U>
    <U>
      <T n="image" p="InEP13\UI\Lessons\EP13_InfantCareObjects_2.png">2f7d0004:00000000:ef8d00c718ce4a89</T>
      <T n="text">0xAE2F5082<!--Infants can learn through play by interacting with the Playmat. Caregivers can bond with an Infant by playing or socializing with an Infant Sim on the Playmat. As your Infant progress towards milestones, they will eventually be able to play alone and show off new surprising behaviors. Try running Tummy Time Together to help your Infant Sim unlock milestones faster!  --></T>
    </U>
  </L>
  <L n="tags">
    <E>Lesson_EP13_GrowingTogether</E>
  </L>
  <T n="ui_sort_order">20</T>
</I>