<?xml version="1.0" encoding="utf-8"?>
<I c="RelationshipBit" i="relbit" m="relationships.relationship_bit" n="familyTrope_difficult" s="310888">
  <T n="autonomy_multiplier">4</T>
  <T n="bit_description">0x1ADD76FF<!--When Sims have a Difficult family dynamic, they simply don't get along like most other family members. When socializing, they will usually lean toward Complaints, or even Mean interactions. They will also be more likely to form Furious sentiments towards each other.--></T>
  <L n="buffs_on_add_bit">
    <U>
      <U n="buff_ref">
        <T n="buff_type">318083<!--buff_FamilyDynamics_Hidden_Difficult--></T>
      </U>
    </U>
  </L>
  <T n="display_name">0x6C1FD3B3<!--Difficult--></T>
  <T n="icon" p="InGame\UI\Icons\Relationships\icon_r_tropeOppressive.png">2f7d0004:00000000:1e965405799f3040</T>
</I>