<?xml version="1.0" encoding="utf-8"?>
<I c="RelationshipBit" i="relbit" m="relationships.relationship_bit" n="sentimentBit_Guilty_ST_MoveIn_ResidencyRejection" s="310881">
  <L n="bit_added_loot_list">
    <T>250407<!--loot_Sentiment_OnAdd_Guilty_generic--></T>
  </L>
  <T n="bit_description">0x27E1DAB6<!--Did {0.SimFirstName} let down {1.SimFirstName} by not agreeing to move in together?--></T>
  <L n="collection_ids">
    <E>Sentiment_Negative</E>
    <E>Sentiment_Guilty</E>
    <E>Sentiment_ShortTerm</E>
  </L>
  <E n="directionality">UNIDIRECTIONAL</E>
  <T n="display_name">0x3CDF714C<!--Residency Rejection--></T>
  <T n="icon" p="InEP13\UI\Icons\Sentiments\Sentiment_ResidencyRejectionGuilt.png">2f7d0004:00000000:74cc36f704b4daa3</T>
  <T n="visible">False</T>
</I>