<?xml version="1.0" encoding="utf-8"?>
<SimData version="0x00000101" u="0x00000019">
  <Instances>
    <I name="adCASPreset_Body" schema="Client_CASThumbnailCamera" type="Object">
      <T name="CameraPosition">1.176932,0.5611861,0.8665509</T>
      <T name="TargetPosition">-0.06524176,0.4841505,-0.02478751</T>
      <T name="CameraFOV">35</T>
    </I>
  </Instances>
  <Schemas>
    <Schema name="Client_CASThumbnailCamera" schema_hash="0x5C3D3343">
      <Columns>
        <Column name="CameraPosition" type="Float3" flags="0x00000000" />
        <Column name="TargetPosition" type="Float3" flags="0x00000000" />
        <Column name="CameraFOV" type="Int32" flags="0x00000000" />
      </Columns>
    </Schema>
  </Schemas>
</SimData>