<?xml version="1.0" encoding="utf-8"?>
<SimData version="0x00000101" u="0x00000000">
  <Instances>
    <I name="SC_24_Cast_Away" schema="Achievement" type="Object">
      <L name="category">
        <T type="TableSetReference">24656</T>
      </L>
      <T name="descriptive_text">0x262AC993</T>
      <T name="display_name">0xFECF8E4B</T>
      <T name="icon">00B2D882-00000000-E0F1CC5101002FEE</T>
      <T name="is_hidden">0</T>
      <L name="objectives">
        <T type="TableSetReference">77702</T>
      </L>
      <T name="pid">10</T>
      <T name="point_value">50</T>
      <T name="reward">0</T>
      <T name="xid">10</T>
    </I>
  </Instances>
  <Schemas>
    <Schema name="Achievement" schema_hash="0xCE59EC31">
      <Columns>
        <Column name="category" type="Vector" flags="0x00000000" />
        <Column name="descriptive_text" type="LocalizationKey" flags="0x00000000" />
        <Column name="display_name" type="LocalizationKey" flags="0x00000000" />
        <Column name="icon" type="ResourceKey" flags="0x00000000" />
        <Column name="is_hidden" type="Boolean" flags="0x00000000" />
        <Column name="objectives" type="Vector" flags="0x00000000" />
        <Column name="pid" type="Int32" flags="0x00000000" />
        <Column name="point_value" type="Int32" flags="0x00000000" />
        <Column name="reward" type="TableSetReference" flags="0x00000000" />
        <Column name="xid" type="String" flags="0x00000000" />
      </Columns>
    </Schema>
  </Schemas>
</SimData>