<?xml version="1.0" encoding="utf-8"?>
<SimData version="0x00000101" u="0x00000000">
  <Instances>
    <I name="puCASPart_Necklace" schema="Client_CASThumbnailCamera" type="Object">
      <T name="CameraPosition">0.01537589,0.5768341,1.53821</T>
      <T name="TargetPosition">-0.01589578,0.5284847,0.04350359</T>
      <T name="CameraFOV">45</T>
    </I>
  </Instances>
  <Schemas>
    <Schema name="Client_CASThumbnailCamera" schema_hash="0x5C3D3343">
      <Columns>
        <Column name="CameraPosition" type="Float3" flags="0x00000000" />
        <Column name="TargetPosition" type="Float3" flags="0x00000000" />
        <Column name="CameraFOV" type="Int32" flags="0x00000000" />
      </Columns>
    </Schema>
  </Schemas>
</SimData>