<?xml version="1.0" encoding="utf-8"?>
<SimData version="0x00000101" u="0x00000000">
  <Instances>
    <I name="ColorFiltering" schema="ColorFiltering" type="Object">
      <L name="tags_to_color_map">
        <U type="Object" schema="ColorFiltering.MapEntry">
          <T name="key_tag">93</T>
          <U name="value_colortuple" schema="ColorFiltering.ColorValue">
            <T name="TagLocalizedName">0x7B55EE51</T>
            <T name="DisplayIndex">9</T>
            <T name="Color">0,0,0</T>
          </U>
        </U>
        <U type="Object" schema="ColorFiltering.MapEntry">
          <T name="key_tag">68</T>
          <U name="value_colortuple" schema="ColorFiltering.ColorValue">
            <T name="TagLocalizedName">0x336462DF</T>
            <T name="DisplayIndex">5</T>
            <T name="Color">0,0,255</T>
          </U>
        </U>
        <U type="Object" schema="ColorFiltering.MapEntry">
          <T name="key_tag">293</T>
          <U name="value_colortuple" schema="ColorFiltering.ColorValue">
            <T name="TagLocalizedName">0x9B185A5E</T>
            <T name="DisplayIndex">10</T>
            <T name="Color">200,185,150</T>
          </U>
        </U>
        <U type="Object" schema="ColorFiltering.MapEntry">
          <T name="key_tag">90</T>
          <U name="value_colortuple" schema="ColorFiltering.ColorValue">
            <T name="TagLocalizedName">0xDCA79E16</T>
            <T name="DisplayIndex">11</T>
            <T name="Color">80,65,15</T>
          </U>
        </U>
        <U type="Object" schema="ColorFiltering.MapEntry">
          <T name="key_tag">92</T>
          <U name="value_colortuple" schema="ColorFiltering.ColorValue">
            <T name="TagLocalizedName">0x72965248</T>
            <T name="DisplayIndex">8</T>
            <T name="Color">128,128,128</T>
          </U>
        </U>
        <U type="Object" schema="ColorFiltering.MapEntry">
          <T name="key_tag">69</T>
          <U name="value_colortuple" schema="ColorFiltering.ColorValue">
            <T name="TagLocalizedName">0x14BBD0DF</T>
            <T name="DisplayIndex">4</T>
            <T name="Color">0,255,0</T>
          </U>
        </U>
        <U type="Object" schema="ColorFiltering.MapEntry">
          <T name="key_tag">95</T>
          <U name="value_colortuple" schema="ColorFiltering.ColorValue">
            <T name="TagLocalizedName">0xD67B6212</T>
            <T name="DisplayIndex">2</T>
            <T name="Color">255,128,0</T>
          </U>
        </U>
        <U type="Object" schema="ColorFiltering.MapEntry">
          <T name="key_tag">106</T>
          <U name="value_colortuple" schema="ColorFiltering.ColorValue">
            <T name="TagLocalizedName">0x545819F8</T>
            <T name="DisplayIndex">1</T>
            <T name="Color">255,105,180</T>
          </U>
        </U>
        <U type="Object" schema="ColorFiltering.MapEntry">
          <T name="key_tag">107</T>
          <U name="value_colortuple" schema="ColorFiltering.ColorValue">
            <T name="TagLocalizedName">0x56862145</T>
            <T name="DisplayIndex">6</T>
            <T name="Color">128,0,255</T>
          </U>
        </U>
        <U type="Object" schema="ColorFiltering.MapEntry">
          <T name="key_tag">65</T>
          <U name="value_colortuple" schema="ColorFiltering.ColorValue">
            <T name="TagLocalizedName">0xE1768A08</T>
            <T name="DisplayIndex">0</T>
            <T name="Color">255,0,0</T>
          </U>
        </U>
        <U type="Object" schema="ColorFiltering.MapEntry">
          <T name="key_tag">105</T>
          <U name="value_colortuple" schema="ColorFiltering.ColorValue">
            <T name="TagLocalizedName">0x8AB48B57</T>
            <T name="DisplayIndex">7</T>
            <T name="Color">255,255,255</T>
          </U>
        </U>
        <U type="Object" schema="ColorFiltering.MapEntry">
          <T name="key_tag">104</T>
          <U name="value_colortuple" schema="ColorFiltering.ColorValue">
            <T name="TagLocalizedName">0xF3857705</T>
            <T name="DisplayIndex">3</T>
            <T name="Color">255,255,0</T>
          </U>
        </U>
      </L>
    </I>
  </Instances>
  <Schemas>
    <Schema name="ColorFiltering" schema_hash="0x158CE37A">
      <Columns>
        <Column name="tags_to_color_map" type="Vector" flags="0x00000000" />
      </Columns>
    </Schema>
    <Schema name="ColorFiltering.MapEntry" schema_hash="0xAB2AF313">
      <Columns>
        <Column name="key_tag" type="UInt32" flags="0x00000000" />
        <Column name="value_colortuple" type="Object" flags="0x00000000" />
      </Columns>
    </Schema>
    <Schema name="ColorFiltering.ColorValue" schema_hash="0x7496DFCD">
      <Columns>
        <Column name="TagLocalizedName" type="LocalizationKey" flags="0x00000000" />
        <Column name="DisplayIndex" type="Int32" flags="0x00000000" />
        <Column name="Color" type="Float3" flags="0x00000000" />
      </Columns>
    </Schema>
  </Schemas>
</SimData>