<?xml version="1.0" encoding="utf-8"?>
<I c="DevelopmentalMilestone" i="developmental_milestone" m="developmental_milestones.developmental_milestone" n="lifeMilestone_ForgottenGrotto" s="313489">
  <L n="ages">
    <E>CHILD</E>
    <E>TODDLER</E>
    <E>TEEN</E>
    <E>YOUNGADULT</E>
    <E>ADULT</E>
    <E>ELDER</E>
  </L>
  <E n="category">Firsts</E>
  <T n="goal">313479<!--lifeMilestoneGoal_ZoneLoaded_ForgottenGrotto--></T>
  <T n="icon" p="InEP13\UI\Icons\DevelopmentalMilestones\milestone_FoundForgottenGrotto.png">2f7d0004:00000000:2694d41c27aa9b13</T>
  <T n="name">0x81B37680<!--Found the Forgotten Grotto--></T>
  <T n="ui_sort_order">50</T>
  <T n="unlocked_text">0xDF6C4CDA<!--{0.SimFirstName} visited the beautiful Forgotten Grotto for the first time.--></T>
  <T n="unlocked_text_no_context">0xDF6C4CDA<!--{0.SimFirstName} visited the beautiful Forgotten Grotto for the first time.--></T>
</I>