<?xml version="1.0" encoding="utf-8"?>
<I c="DevelopmentalMilestone" i="developmental_milestone" m="developmental_milestones.developmental_milestone" n="infantMilestones_Generic_FirstVisitToFamilyMember" s="286475">
  <L n="ages">
    <E />
  </L>
  <E n="category">Firsts</E>
  <T n="goal">334935<!--infantMilestonesGoal_Event_FirstVisitToFamilyMember--></T>
  <T n="icon" p="InEP13\UI\Icons\DevelopmentalMilestones\milestone_FirstVisitToFamilyMembersHouse.png">2f7d0004:00000000:fe2d783290df38f3</T>
  <L n="loot">
    <T>286522<!--loot_InfantMilestones_FirstVisitToFamilyMember--></T>
    <T>319226<!--loot_infantMilestones_Anticipation_EndWatch--></T>
  </L>
  <T n="name">0x9F19D228<!--First Visit to a Family Member's Home--></T>
  <T n="ui_sort_order">30</T>
  <T n="unlocked_text">0xE47276D8<!--{0.SimFirstName} went on a trip to {3.String} to visit {0.SimPronounPossessiveDependent} relatives.--></T>
  <T n="unlocked_text_no_context">0x15EE410<!--{0.SimFirstName} went on a trip to visit {0.SimPronounPossessiveDependent} relatives.--></T>
</I>