<?xml version="1.0" encoding="utf-8"?>
<I c="DevelopmentalMilestone" i="developmental_milestone" m="developmental_milestones.developmental_milestone" n="infantMilestones_Generic_FirstBlowout" s="286467">
  <L n="ages">
    <E />
  </L>
  <E n="category">Firsts</E>
  <T n="goal">286607<!--infantMilestonesGoal_Interaction_Generic_FirstBlowout--></T>
  <T n="icon" p="InEP13\UI\Icons\DevelopmentalMilestones\milestone_FirstBlowOut.png">2f7d0004:00000000:d6f012e7f987534e</T>
  <L n="loot">
    <T>286515<!--loot_InfantMilestones_FirstBlowout--></T>
    <T>319226<!--loot_infantMilestones_Anticipation_EndWatch--></T>
  </L>
  <T n="name">0x3344C0DC<!--First Diaper Blowout--></T>
  <T n="ui_sort_order">40</T>
  <T n="unlocked_text">0xB7FBD6C6<!--{0.SimFirstName} experienced {0.SimPronounPossessiveDependent} first diaper blowout. That foul stench won't be forgotten by those who were <i>unfortunately</i> present.--></T>
  <T n="unlocked_text_no_context">0xB7FBD6C6<!--{0.SimFirstName} experienced {0.SimPronounPossessiveDependent} first diaper blowout. That foul stench won't be forgotten by those who were <i>unfortunately</i> present.--></T>
</I>