<?xml version="1.0" encoding="utf-8"?>
<I c="DevelopmentalMilestone" i="developmental_milestone" m="developmental_milestones.developmental_milestone" n="lifeMilestone_Toddler_FirstNightmare" s="305670">
  <L n="ages">
    <E>TODDLER</E>
  </L>
  <E n="category">Firsts</E>
  <T n="goal">305595<!--lifeMilestoneGoal_Actor_Toddler_FirstNightmare--></T>
  <T n="icon" p="InEP13\UI\Icons\DevelopmentalMilestones\milestone_FirstNightmare.png">2f7d0004:00000000:35fab17b3ff93c65</T>
  <L n="loot" />
  <T n="name">0x570E42B7<!--First Nightmare--></T>
  <T n="ui_sort_order">4</T>
  <T n="unlocked_text">0xF678893D<!--Life's not all fun and games, not even when {0.SimFirstName} is asleep. Scary stuff!--></T>
  <T n="unlocked_text_no_context">0xF678893D<!--Life's not all fun and games, not even when {0.SimFirstName} is asleep. Scary stuff!--></T>
</I>