<?xml version="1.0" encoding="utf-8"?>
<I c="DevelopmentalMilestone" i="developmental_milestone" m="developmental_milestones.developmental_milestone" n="lifeMilestone_Toddler_FirstFriend" s="305710">
  <L n="ages">
    <E>TODDLER</E>
  </L>
  <E n="category">Social</E>
  <T n="goal">303946<!--lifeMilestoneGoal_Rel_Toddler_FirstFriend--></T>
  <T n="icon" p="InEP13\UI\Icons\DevelopmentalMilestones\milestone_FirstFriend.png">2f7d0004:00000000:a10361ff97770f7e</T>
  <V n="is_primary_milestone" t="True">
    <U n="True">
      <T n="hint_text">0xB426924A<!--Now that {0.SimPronounSubjective} learned how to talk, can {0.SimFirstName} make a new friend?--></T>
      <V n="revealable_name" t="enabled">
        <T n="enabled">0xE9DBCF98<!--First Childhood Friend--></T>
      </V>
      <L n="tests">
        <L>
          <V t="developmental_milestone">
            <U n="developmental_milestone">
              <T n="developmental_milestone">305673<!--lifeMilestone_Toddler_LearnedToTalk--></T>
            </U>
          </V>
        </L>
      </L>
    </U>
  </V>
  <L n="loot">
    <T>313673<!--loot_LifeMilestone_CelebrateToddler--></T>
  </L>
  <T n="name">0xA8564888<!--First Childhood Friend--></T>
  <L n="prerequisite_milestones">
    <T>305673<!--lifeMilestone_Toddler_LearnedToTalk--></T>
  </L>
  <T n="ui_sort_order">3</T>
  <T n="unlocked_text">0x5263B678<!--{1.SimName} became {0.SimFirstName}'s first friend outside of family.--></T>
  <T n="unlocked_text_no_context">0x4A017AD2<!--{0.SimFirstName} made a friend outside of the family!--></T>
</I>